ascii_art/__init__.py
ascii_art/generator.py
ascii_generator/__init__.py
ascii_generator/main.py
ASCII_art_tool-1.0.1.dist-info/METADATA
ASCII_art_tool-1.0.1.dist-info/WHEEL
ASCII_art_tool-1.0.1.dist-info/top_level.txt
ASCII_art_tool-1.0.1.dist-info/RECORD
