Metadata-Version: 2.1
Name: ASCII-art-tool
Version: 1.0.1
Summary: The ASCII art tool is a simple library to generate ASCII art from regular images.
Home-page: https://github.com/Nabil-Lahssini/ASCII_art_tool
Author: Nabil Lahssini
Author-email: NabilLahssini@gmail.com
License: MIT
Platform: UNKNOWN
Classifier: License :: OSI Approved :: MIT License
Classifier: Programming Language :: Python :: 3
Classifier: Programming Language :: Python :: 3.7
